{
  "Info": {
    "Magic": "AIB ",
    "Version": "0x407",
    "Filename": "Npc_Raul.utility.root",
    "File Category": "AI"
  },
  "Commands": [
    {
      "Name": "Root",
      "GUID": "74ed28ea-f167-4d76-cdb0-36d4e4474717",
      "Left Node Index": 1,
      "Right Node Index": -1
    }
  ],
  "Modules": [
    {
      "File Path": "NPCCommon.utility.module.ainb",
      "File Category": "AI",
      "Count": 1
    }
  ],
  "Nodes": [
    {
      "Node Type": "UserDefined",
      "Node Index": 0,
      "Flags": [
        "Is Module"
      ],
      "Name": "NPCCommon.utility.module",
      "GUID": "7b13e230-d4de-40b8-3aac-656882e9cc6e"
    },
    {
      "Node Type": "Element_SplitTiming",
      "Node Index": 1,
      "Flags": [
        "Is Resident Node"
      ],
      "Name": "",
      "GUID": "72cd8dc4-ca7a-437e-4693-b322ac06a569",
      "Internal Parameters": {
        "int": [
          {
            "Name": "ChildStateSyncPolicy",
            "Value": 0
          }
        ]
      },
      "Linked Nodes": {
        "Standard Link": [
          {
            "Node Index": 8,
            "Connection Name": "Enter"
          },
          {
            "Node Index": 7,
            "Connection Name": "Update"
          },
          {
            "Node Index": 2,
            "Connection Name": "Leave"
          }
        ]
      }
    },
    {
      "Node Type": "UserDefined",
      "Node Index": 2,
      "Name": "ExecuteGenericDummyAction",
      "GUID": "d074a2a4-ef39-4bd5-cb0-15e682868dcb"
    },
    {
      "Node Type": "UserDefined",
      "Node Index": 3,
      "Flags": [
        "Is Precondition Node"
      ],
      "Name": "QueryAIScheduleGetSettingPostureTypeWhenWait",
      "GUID": "fc83a848-4a8c-4d04-f580-d5a566b6c641",
      "Internal Parameters": {
        "bool": [
          {
            "Name": "OutputOnlyOnEnter",
            "Value": false
          }
        ]
      },
      "Output Parameters": {
        "int": [
          {
            "Name": "Posture",
            "Is Output": true
          }
        ]
      },
      "Linked Nodes": {
        "Bool/Float Input Link and Output Link": [
          {
            "Node Index": 4,
            "Parameter": "Posture"
          }
        ]
      }
    },
    {
      "Node Type": "Element_S32Selector",
      "Node Index": 4,
      "Name": "",
      "GUID": "b497f407-cc4a-426b-12b7-41a59c99d2ea",
      "Precondition Nodes": [
        0
      ],
      "Internal Parameters": {
        "int": [
          {
            "Name": "CalculateTiming",
            "Value": 0
          },
          {
            "Name": "InputValue",
            "Value": 0
          }
        ],
        "bool": [
          {
            "Name": "ChildFrameSync",
            "Value": false
          },
          {
            "Name": "IsNoSelectIfSameInstance",
            "Value": false
          },
          {
            "Name": "IsNoSelectWhenChildBusy",
            "Value": false
          }
        ]
      },
      "Input Parameters": {
        "int": [
          {
            "Name": "Input",
            "Node Index": 3,
            "Parameter Index": 0,
            "Value": 0
          }
        ]
      },
      "Linked Nodes": {
        "Standard Link": [
          {
            "Node Index": 5,
            "Condition": 2
          },
          {
            "Node Index": 6,
            "Condition": "Default"
          }
        ],
        "Int Input Link": [
          {
            "Node Index": 3,
            "Parameter": "Input"
          }
        ]
      }
    },
    {
      "Node Type": "UserDefined",
      "Node Index": 5,
      "Name": "OneShotClothSetEnableGround",
      "GUID": "b3e47fbf-8db3-4fd2-20ad-4bbb174e8b5a",
      "Internal Parameters": {
        "bool": [
          {
            "Name": "ExecuteEveryFrame",
            "Value": true
          }
        ]
      },
      "Input Parameters": {
        "bool": [
          {
            "Name": "IsEnable",
            "Node Index": -1,
            "Parameter Index": 0,
            "Flags": [
              "Pulse TLS"
            ],
            "Value": true
          }
        ]
      }
    },
    {
      "Node Type": "UserDefined",
      "Node Index": 6,
      "Name": "OneShotClothSetEnableGround",
      "GUID": "438b9c2d-cb37-4df6-8d9f-86a710e21d42",
      "Internal Parameters": {
        "bool": [
          {
            "Name": "ExecuteEveryFrame",
            "Value": true
          }
        ]
      },
      "Input Parameters": {
        "bool": [
          {
            "Name": "IsEnable",
            "Node Index": -1,
            "Parameter Index": 0,
            "Flags": [
              "Pulse TLS"
            ],
            "Value": false
          }
        ]
      }
    },
    {
      "Node Type": "Element_Simultaneous",
      "Node Index": 7,
      "Name": "",
      "GUID": "24047b13-d15a-49ad-8bb7-f68a2e366cfa",
      "Internal Parameters": {
        "int": [
          {
            "Name": "EndPolicy",
            "Value": 0
          },
          {
            "Name": "ResultPolicy",
            "Value": 0
          }
        ]
      },
      "Linked Nodes": {
        "Standard Link": [
          {
            "Node Index": 4,
            "Connection Name": ""
          },
          {
            "Node Index": 0,
            "Connection Name": ""
          }
        ]
      }
    },
    {
      "Node Type": "UserDefined",
      "Node Index": 8,
      "Name": "ExecuteGenericDummyAction",
      "GUID": "219acc4e-462d-4b56-8285-895b9516f077"
    }
  ],
  "File Hashes": {
    "Unknown File Hash": "0xc59721fe"
  }
}