{
  "Metadata": {
    "Filename": "DmF_ZO_MiddleBossOut_UMii_Zora_BodyC_W_000.root",
    "Version": "0x417",
    "HasASNodeBaev": false
  },
  "Blackboard": {},
  "Bone Groups": [],
  "Expressions": [],
  "Partials": [],
  "Transitions": [],
  "Valid Tags": [],
  "Commands": [
    {
      "Name": "C05-NPC_Zora_Attendant_wait",
      "Unknown 1": -1.0,
      "Ignore Same Command": false,
      "Interpolation Type": 0,
      "GUID": "e512e711-3324-41d5-9f03-d6006f2964e4",
      "Node Index": 4
    },
    {
      "Name": "C06-NPC_Zora_Attendant_nod",
      "Unknown 1": -1.0,
      "Ignore Same Command": false,
      "Interpolation Type": 0,
      "GUID": "1c843f52-6b4b-40ef-b3d7-8f3eb290fc80",
      "Node Index": 2
    }
  ],
  "Nodes": [
    {
      "Node Index": 0,
      "Node Type": "SkeletalAnimation",
      "No State Transition": true,
      "GUID": "ae9e2401-677f-40e0-81d5-2487b5d78ed4",
      "Sync Controls": [
        {
          "GUID": "4cd824db-2d17-4298-b1de-c7b6494180c4",
          "Fade In Frame": 10.0,
          "Unknown": 0
        }
      ],
      "Body": {
        "Animation": "C06-UMii_Zora_BodyC_W_000-A-0",
        "Unknown 1": 0,
        "Unknown 2": 0,
        "Unknown 3": false,
        "Unknown 4": 0.0,
        "Events": [
          3
        ]
      }
    },
    {
      "Node Index": 1,
      "Node Type": "SkeletalAnimation",
      "No State Transition": true,
      "GUID": "f3f78bc7-6fb8-4551-8e6a-382459004de9",
      "Body": {
        "Animation": "C06-UMii_Zora_BodyC_W_000-A-0_Loop",
        "Unknown 1": 0,
        "Unknown 2": 0,
        "Unknown 3": false,
        "Unknown 4": 0.0,
        "Events": [
          3
        ]
      }
    },
    {
      "Node Index": 2,
      "Node Type": "Sequential",
      "No State Transition": true,
      "GUID": "0dc8c5c9-0422-4341-93c5-6fba8586d9f6",
      "Body": {
        "Use Sync Range Mult": false,
        "Sync Range Mult": 0,
        "Unknown 3": 0,
        "Child Nodes": [
          0,
          1
        ]
      }
    },
    {
      "Node Index": 3,
      "Node Type": "Event",
      "No State Transition": true,
      "GUID": "ad292aea-d90d-4dd2-b2bc-fe81a318320b",
      "Body": {
        "Event": {}
      }
    },
    {
      "Node Index": 4,
      "Node Type": "SkeletalAnimation",
      "No State Transition": true,
      "GUID": "79f0d179-dd4b-4f0c-95d3-105eac26d122",
      "Body": {
        "Animation": "C06-UMii_Zora_BodyC_W_000-A-0_Loop",
        "Unknown 1": 0,
        "Unknown 2": 0,
        "Unknown 3": false,
        "Unknown 4": 0.0,
        "Events": [
          3
        ]
      }
    }
  ]
}